{
  "product_info": {
    "model": "ZT111",
    "title": "ZT111 INDUSTRIAL PRINTER",
    "tagline": "the smart choice",
    "url": "www.zebra.com/zt111",
    "description": "--- Page 1 ---\nPRODUCT SPEC SHEET\nZT111 INDUSTRIAL PRINTER\nZT111 Industrial Printer\nBudget can be brilliant, too\nWhen your labeling needs demand more than a desktop printer can deliver and you’re looking to add an industrial printer, you\nshouldn’t have to compromise between budget and quality. With Zebra’s ZT111, you don’t have to. Get just the right features you\nneed at the right price to match your needs – today and tomorrow. Stay productive with fast print speeds, built-in intelligence and\ntime-saving tools to make work easier. And, futureproof your investment with upgradeability.\nMake the smart choice with the ZT111, the entry-level printer that’s easy on your budget and gives you more. More uptime, more\nprocessing power, more tools and more years of use.\nSave Time and Effort for IT\nYour IT team is busy enough. The ZT111 makes it simple. It’s\neasy to integrate into your existing network as it is backwards\ncompatible and features Printer Emulations to replace other\nbrands without having to change label formats or rewrite\ncode. Make training simple with the easy-to-use 3-button\ninterface with 5 status icons.\nPrint More for Longer\nEliminate replacing printers that don’t last. Get the enduring\nquality you expect and deserve from Zebra at a price that\nmatches your budget, knowing this printer will outperform\nothers for years to come. Be confident knowing you’re backed\nby Zebra, the #1 leader in barcode printing.\nThe Budget Printer that Delivers More\nMaximize Your Workspace\nSave workspace with the ZT111’s small footprint, compact\nGreater Functionality at a Fraction of the Cost\ndimensions, and bi-fold door that reduces the height needed\nGet more value out of your printer with built-in Zebra-only\nto open it.\nsoftware tools that make it easy to integrate and operate.\nFrom setup utilities to built-in security settings to ongoing\nThe Right Capabilities to Move Business\nvisibility into your supplies usage, Zebra gives you more\nwithout the added cost. Forward\nInnovative Processing to Power Future Printing\nThe ZT111 includes an all-new architecture to process more\njobs at once and evolve with advancing technology. So, it’s a\nsmart choice now and later.\nSpend less. Get more. Print longer.\nFor more information, please visit www.zebra.com/zt111\n--- Page 2 ---\nOnboard analytics and printhead element out detection help Supplies, Service and Support\nyou plan maintenance in advance. And, the easy tool-less\nplaten and print head removal makes the job easy.\nZebra Certified Supplies\nPrinting supplies provide a digital voice for assets across your\nThe Key Features You Want\nsupply chain. You rely on them to disseminate critical data\nWant 300 dpi high-resolution printing? You’ve got it, and more.\nthroughout your organization. If something goes wrong with\nWith fast print speeds up to 10 ips at 203 dpi, intuitive media\nyour printing supplies, operations are interrupted, productivity\nloading with color-coded touch points and adjustable media\nsuffers and costs rise. That’s why we design, produce and\nsensors, you can quickly print what you need without the\nrigorously pretest our own line of labels and tags to ensure\nhassle.\nconsistent, optimized performance in your Zebra printer. For\nindustry-leading quality, service and thermal printing\nConnect Your Way\nexpertise, choose Zebra Certified Supplies.\nConnecting your devices, printers and people is a critical factor\nto driving productivity. The ZT111 makes it easy with plenty of Backed by Zebra’s Worldwide Service and Support\nconnectivity options to choose from like Serial and Ethernet.\nAccess repair support services anywhere around the globe\nNeed a USB Host port? It’s got that. You can even tap to pair\nthrough Zebra and its trusted network of more than 10,000\nand print with compatible mobile devices with the Print Touch\npartners. Zebra OneCare™ Maintenance Plans provide\ntag (NFC). Or, add a second Ethernet port or 802.11ac Wi-Fi™.\nenhanced coverage that exceeds standard warranty.\nFutureproof Your Investment\nNew to industrial printing? No worries. Save on large, upfront\ncapital costs by purchasing just the features you need right\nnow. With field-installable upgradeability options like wireless\nconnectivity and media handling, your printer can adapt to\nyour changing needs whenever you need it.\nBuilt-in Security to Protect Your Data and\nInfrastructure\nSmart Settings to Prevent Tampering\nSecurity risks are real and costly. Endpoints are becoming\npopular targets, including networked thermal printers. Protect\nyour ZT111 during start up with Secure Boot and prevent\nunwanted settings changes while in use with Protected Mode.\nWhen you’re ready to relocate or retire your ZT111, easily reset\nall user settings and remove user files with Simplified Printer\nDecommissioning. Protect your networks from costly cyber\nattacks with Zebra Secure Service Commands, part of\nPrintSecure.\n--- Page 3 ---\nSpecifications\nMarkets and\nApplications\nStandard Features Operating Characteristics\n• Print methods: direct-thermal or thermal-transfer Operating Thermal transfer: 40ºF to 105ºF/5º to 40ºC\nManufacturing\n• Construction: metal frame and plastic enclosures Temp. Direct thermal: 32ºF to 105ºF/0º to 40ºC\n• Bi-fold media door with large clear window\n• Side-loading supplies path for simplified media and ribbon Storage/Transp -40ºF to 140ºF/-40º to 60ºC • Work-in-process\nloading ortation • Product ID/serial numbers\n• Thin film printhead with E3™ Element Energy™ Equalizer for Temperature • Packaging labeling\nsuperior print quality • Receiving/put-away labeling\n• Five color LEDs for quick printer status •\n• Three button keypad Operating 20% to 85% non-condensing\n• Communications: USB 2.0 and RS-232 Serial port, 10/100 Humidity\nTransportation and Logistics\nEthernet, and USB Host\n• ENERGY STAR™ certified Storage 5% to 85% non-condensing\n• Bluetooth™ Low Energy Humidity • Order picking/packing\n• ZebraDesigner Essentials – easy label design tool free at • Shipping/receiving\nwww.zebra.com/zebradesigner Electrical Universal auto-ranging (PFC-compliant) power • Cross-docking\nsupply 100-240 VAC; 50-60 Hz • Compliance labeling\nENERGY STAR certified •\nPhysical Characteristics Agency IEC 62368-1, EN55022 Class B, EN55024, Healthcare\nApprovals EN55035, EN61000-3-2, EN61000-3-3, FCC\nClass B, ICES-003, FCC 15.209; 15.247(d), IC\n• Laboratory labeling\nDimensions ZT111 Closed: 17 in. L x 9.5 in. W x 11 in. H RSS 247, EN 300 328, EN 301 893, EN 62311,\n432 mm L x 241 mm W x 279 mm H cTUVus, CE Marking, UKCA, VCCI, RCM, S- • Blood bank labeling\n• Asset tracking\nMark, CCC, CU EAC, BSMI, KCC, and BIS\n• Unit-dose labeling\nWeight ZT111: 17 lbs./7.7 kg\n• Pharmacy labeling\n•\n*Dimensions are for the base model printer. Print DNA™ Basic Software\nConsult your sales representative for specifics\nregarding other configurations. Retail\nThis printer is supported by our Print DNA Basic suite of software\ncapabilities to get your printer up and running quickly, deliver a • Buy online pick up in store\ndependable print experience and enable your printer to evolve labeling\nPrinter Specifications with your business needs. Print DNA features may vary by model, • Return tagging\nand some features may require a license. For more information, • Price labeling\nResolution 203 dpi/8 dots per mm please visit • Shipping labeling\nwww.zebra.com/printdna\n300 dpi/12 dots per mm (optional) •\nMemory 256 MB SDRAM memory\n256 MB on-board linear Flash memory Firmware\nMaximum Print 4.09 in./104 mm ZBI 2.0™ — Optional powerful programming language that lets\nWidth printers run stand-alone applications, connect to peripherals, and\nmuch more.\nMaximum Print 10 ips (200 dpi) ZPL and ZPL II™ — Zebra Programming Language provides\nSpeed 6 ips (300 dpi) sophisticated label formatting and printer control and is\ncompatible with all Zebra printers.\nMedia Sensors Transmissive and reflective sensors EPL and EPL2™— Eltron Programming Language simplifies label\nformatting and enables format compatibility with legacy\napplications. (EPL available on 203 dpi models only.)\nMaximum Print 203 dpi: 157in./3988 mm\nLength 300 dpi: 73in./1854 mm\nBarcode Symbologies\nMedia Characteristics\nLinear Barcodes: Code 11, Code 39, Code 93, Code 128 with\nsubsets A/B/C and UCC Case Codes, ISBT-128, UPC-A, UPC-E,\nMinimum Label Tear mode: 0.7 in/18 mm EAN-8, EAN-13, UPC and EAN with 2 or 5 digit extensions, Plessey,\nand Cutter mode: 1 in/25 mm Postnet, Standard 2-of-5, Industrial 2-of-5, Interleaved 2-of-5,\nLiner Length Peel mode: 0.5 in/13 mm Logmars, MSI, Codabar, Planet Code\n2D Barcodes: Aztec, Codablock, PDF417, Code 49, Data Matrix,\nMedia Width 0.75 in./19.4 mm to 4.50 in./114 mm MaxiCode, QR Code, MicroPDF417, TLC 39, RSS-14 (and\ncomposite)\nMedia Roll Size 8.0 in./203 mm O.D. on a 3.0 in./76 mm I.D.\ncore\n6.0 in./152 mm O.D. on a 1.0 in./25 mm I.D. Fonts and Graphics\ncore\nMedia Thickness 0.003 in./0.076 mm to 0.010 in./0.25 mm 7 bitmapped, 1 smooth-scalable (CG Triumvirate™ Bold\nCondensed*) Pre-loaded Unicode™-compliant scalable fonts for\nEMEA character sets International character sets supporting the\nMedia Types Continuous, die-cut, notch, black mark\nfollowing code page: IBM™ Code Page 850\nSupports user-defined fonts and graphics, including custom\nlogos ZPL II drawing commands including boxes and lines 64 MB\nRibbon Characteristics (Thermal-transfer user available Flash memory storage for downloadable objects;\n32 MB user-available SDRAM\noption only)\nStandard 1,476 ft./450 m\nLength\nWidth 2 in./51 mm to 4.33 in./110 mm\nCore 1.0 in./25.4 mm\n--- Page 4 ---\nOptions and Accessories\nCommunication\n• 802.11ac Wi-Fi option card\n• 10/100 Ethernet option card\nMedia Handling\n• Peel — a front-mount, passive-peel with no take-up spindle\n• Cutter — a front-mount guillotine cutter\nKeyboard Display Unit\n• ZKDU™ keyboard display units for stand-alone printing\napplications\nThe Zebra wordmark and logo are trademarks of Zebra Technologies Corp., registered in many jurisdictions worldwide. Android is a\ntrademark of Google LLC. All other trademarks are the property of their respective owners. ©2025 Zebra Technologies Corp. and/or its\naffiliates.\n03/20/2023 HTML"
  },
  "specifications": {
    "printer": {
      "resolution": {
        "raw": "203 dpi/8 dots per mm\n300 dpi/12 dots per mm (optional)",
        "dpi": 203,
        "dots_per_mm": 8
      },
      "memory": "256 MB SDRAM memory\n256 MB on-board linear Flash memory",
      "maximum_print_width": "4.09 in./104 mm",
      "media_sensors": [
        "Transmissive and reflective sensors"
      ]
    },
    "physical": {
      "dimensions": "ZT111 Closed: 17 in. L x 9.5 in. W x 11 in. H\n432 mm L x 241 mm W x 279 mm H",
      "weight": "ZT111: 17 lbs./7.7 kg"
    },
    "media": {
      "maximum_label_length": "Tear mode: 0.7 in/18 mm\nCutter mode: 1 in/25 mm\nPeel mode: 0.5 in/13 mm",
      "media_width": {
        "raw": "0.75 in./19.4 mm to 4.50 in./114 mm",
        "min_inches": 0.75,
        "max_inches": 4.5
      },
      "media_roll_size": "8.0 in./203 mm O.D. on a 3.0 in./76 mm I.D.\ncore\n6.0 in./152 mm O.D. on a 1.0 in./25 mm I.D.\ncore",
      "thickness": "0.003 in./0.076 mm to 0.010 in./0.25 mm",
      "media_types": [
        "Continuous, die-cut, notch, black mark"
      ]
    },
    "ribbon": {},
    "operating_conditions": {
      "operating_temperature": {
        "raw": "Thermal transfer: 40ºF to 105ºF/5º to 40ºC\nDirect thermal: 32ºF to 105ºF/0º to 40ºC"
      },
      "storage_temperature": {
        "raw": "-40ºF to 140ºF/-40º to 60ºC"
      },
      "operating_humidity": {
        "raw": "20% to 85% non-condensing",
        "min_percent": 20,
        "max_percent": 85,
        "condition": "non-condensing"
      },
      "storage_humidity": {
        "raw": "5% to 85% non-condensing",
        "min_percent": 5,
        "max_percent": 85,
        "condition": "non-condensing"
      },
      "electrical": "Universal auto-ranging (PFC-compliant) power\nsupply 100-240 VAC; 50-60 Hz\nENERGY STAR certified"
    }
  },
  "features": {
    "standard": [
      "Print methods: direct-thermal or thermal-transfer",
      "Construction: metal frame and plastic enclosures",
      "Bi-fold media door with large clear window",
      "Side-loading supplies path for simplified media and ribbon loading",
      "Thin film printhead with E3™ Element Energy™ Equalizer for superior print quality",
      "Five color LEDs for quick printer status",
      "Three button keypad",
      "Communications: USB 2.0 and RS-232 Serial port, 10/100 Ethernet, and USB Host",
      "ENERGY STAR™ certified",
      "Bluetooth™ Low Energy",
      "ZebraDesigner Essentials – easy label design tool free at www.zebra.com/zebradesigner"
    ],
    "optional": []
  },
  "fonts_and_barcodes": {
    "fonts": [],
    "barcode_ratios": [],
    "barcodes_1d": [],
    "barcodes_2d": [],
    "graphics_memory": ""
  },
  "connectivity": [
    "Ethernet",
    "Wi-Fi",
    "Bluetooth",
    "Serial"
  ],
  "compliance": {
    "regulatory_standards": [],
    "certifications": [],
    "energy_star": true
  },
  "warranty": {},
  "additional_information": {
    "copyright": "©2025 Zebra Technologies Corp. and/or its",
    "trademark": "The Zebra wordmark and logo are trademarks of Zebra Technologies Corp.",
    "document_date": "03/20/2023"
  },
  "metadata": {
    "source_file": "zt111-spec-sheet-en-us.pdf",
    "extraction_date": "2025-10-16T13:47:53.574025",
    "schema_version": "1.0.0",
    "total_pages": 4,
    "total_tables": 11
  }
}